MANIFEST.in
README.rst
setup.py
cciaa/__init__.py
cciaa.intranetworkflow.egg-info/PKG-INFO
cciaa.intranetworkflow.egg-info/SOURCES.txt
cciaa.intranetworkflow.egg-info/dependency_links.txt
cciaa.intranetworkflow.egg-info/entry_points.txt
cciaa.intranetworkflow.egg-info/namespace_packages.txt
cciaa.intranetworkflow.egg-info/not-zip-safe
cciaa.intranetworkflow.egg-info/requires.txt
cciaa.intranetworkflow.egg-info/top_level.txt
cciaa/intranetworkflow/__init__.py
cciaa/intranetworkflow/config.py
cciaa/intranetworkflow/configure.zcml
cciaa/intranetworkflow/localroles.py
cciaa/intranetworkflow/permissions.zcml
cciaa/intranetworkflow/setuphandlers.py
cciaa/intranetworkflow/tests.py
cciaa/intranetworkflow/browser/__init__.py
cciaa/intranetworkflow/browser/configure.zcml
cciaa/intranetworkflow/browser/full_cciaa_review_list.pt
cciaa/intranetworkflow/browser/my_camcom_worklist.py
cciaa/intranetworkflow/browser/reviewlist.py
cciaa/intranetworkflow/portlets/__init__.py
cciaa/intranetworkflow/portlets/camcom_portlet_review.pt
cciaa/intranetworkflow/portlets/configure.zcml
cciaa/intranetworkflow/portlets/worklist.py
cciaa/intranetworkflow/profiles/default/cciaa.intranetworkflow_various.txt
cciaa/intranetworkflow/profiles/default/metadata.xml
cciaa/intranetworkflow/profiles/default/propertiestool.xml
cciaa/intranetworkflow/profiles/default/rolemap.xml
cciaa/intranetworkflow/profiles/default/sharing.xml
cciaa/intranetworkflow/profiles/default/workflows.xml
cciaa/intranetworkflow/profiles/default/workflows/camcom_folder_workflow/definition.xml
cciaa/intranetworkflow/profiles/default/workflows/camcom_public_workflow/definition.xml
cciaa/intranetworkflow/profiles/default/workflows/camcom_public_workflow/scripts/notificaHome.py
cciaa/intranetworkflow/profiles/uninstall/portlets.xml
cciaa/intranetworkflow/profiles/uninstall/propertiestool.xml
cciaa/intranetworkflow/profiles/uninstall/skins.xml
cciaa/intranetworkflow/profiles/uninstall/workflows.xml
docs/HISTORY.rst
docs/INSTALL.txt
docs/LICENSE.txt
docs/LICENZA.txt