Metadata-Version: 1.1
Name: cciaa.intranetworkflow
Version: 3.0.0
Summary: Workflow of the CCIAA - C4P project
Home-page: https://github.com/PloneGov-IT/cciaa.intranetworkflow
Author: RedTurtle Technology
Author-email: sviluppoplone@redturtle.it
License: GPL
Keywords: c2p c3p c4p cciaa workflow
Platform: UNKNOWN
Classifier: Framework :: Plone
Classifier: Framework :: Plone :: 5.1
Classifier: Framework :: Plone :: 5.2
Classifier: Programming Language :: Python
Classifier: Topic :: Software Development :: Libraries :: Python Modules
